CHANGES.txt
README.txt
setup.py
Products/__init__.py
Products.RichImage.egg-info/PKG-INFO
Products.RichImage.egg-info/SOURCES.txt
Products.RichImage.egg-info/dependency_links.txt
Products.RichImage.egg-info/namespace_packages.txt
Products.RichImage.egg-info/not-zip-safe
Products.RichImage.egg-info/requires.txt
Products.RichImage.egg-info/top_level.txt
Products/RichImage/__init__.py
Products/RichImage/cache.py
Products/RichImage/config.py
Products/RichImage/configure.zcml
Products/RichImage/events.py
Products/RichImage/field.py
Products/RichImage/interfaces.py
Products/RichImage/setuphandlers.py
Products/RichImage/widget.py
Products/RichImage/browser/__init__.py
Products/RichImage/browser/configure.zcml
Products/RichImage/browser/crops.py
Products/RichImage/content/__init__.py
Products/RichImage/content/configure.zcml
Products/RichImage/content/richimage.py
Products/RichImage/profiles/default/catalog.xml
Products/RichImage/profiles/default/factorytool.xml
Products/RichImage/profiles/default/import_steps.xml
Products/RichImage/profiles/default/metadata.xml
Products/RichImage/profiles/default/portlets.xml
Products/RichImage/profiles/default/propertiestool.xml
Products/RichImage/profiles/default/richimage_various.txt
Products/RichImage/profiles/default/rolemap.xml
Products/RichImage/profiles/default/skins.xml
Products/RichImage/profiles/default/types.xml
Products/RichImage/profiles/default/types/RichImage.xml
Products/RichImage/skins/RichImage/docrop.py
Products/RichImage/skins/RichImage/edit_crop.pt
Products/RichImage/skins/RichImage/jquery-imgareaselect.js
Products/RichImage/skins/RichImage/richimage_edit.pt
Products/RichImage/tests/__init__.py
Products/RichImage/tests/base.py
Products/RichImage/tests/browser.txt
Products/RichImage/tests/layer.py
Products/RichImage/tests/test_RichImage.py
Products/RichImage/tests/test_blobs.py
Products/RichImage/tests/test_doctest.py
Products/RichImage/tests/test_linguaplone.py
Products/RichImage/tests/utils.py
Products/RichImage/tests/input/image.jpg
Products/RichImage/tests/input/image.png
Products/RichImage/tests/input/image_small.png
Products/RichImage/tests/selenium/richimage.html
docs/LICENSE.GPL
docs/LICENSE.txt