Metadata-Version: 1.0
Name: Products.RichImage
Version: 1.5
Summary: Image with crop functionalities.
Home-page: http://www.jarn.com
Author: Jarn AS
Author-email: info@jarn.com
License: GPL
Platform: UNKNOWN
Classifier: Framework :: Plone
Classifier: Intended Audience :: Developers
Classifier: License :: OSI Approved :: GNU General Public License (GPL)
